LICENSE.txt
MANIFEST.in
README.txt
RELEASE.txt
setup.py
LSDapi.egg-info/PKG-INFO
LSDapi.egg-info/SOURCES.txt
LSDapi.egg-info/dependency_links.txt
LSDapi.egg-info/requires.txt
LSDapi.egg-info/top_level.txt
LSDyf/__init__.py