Metadata-Version: 2.1
Name: LSDapi
Version: 0.0.2
Summary: Yahoo Finance live stock data
Home-page: UNKNOWN
Author: Mehdi Ghaouti
Author-email: ghaouti.mehdi@gmail.com
License: MIT
Keywords: yahoo finance stocks
Platform: UNKNOWN
Classifier: Development Status :: 5 - Production/Stable
Classifier: Intended Audience :: Education
Classifier: Operating System :: Microsoft :: Windows :: Windows 10
Classifier: License :: OSI Approved :: MIT License
Classifier: Programming Language :: Python :: 3
